api/__init__.py
api/database_config.py
api/file.py
api/knowledge.py
api/llm_model.py
api/rewrite.py
api/router.py
api/scheduler.py
api/services/__init__.py
api/services/database_config.py
api/services/file.py
api/services/knowledge.py
api/services/llm_model.py
api/services/rewrite.py
api/utils/__init__.py
api/utils/code.py
api/utils/core.py
api/utils/response.py
api/utils/retry.py
api/utils/scheduler.py
api/utils/util.py
document_loaders/__init__.py
document_loaders/base.py
document_loaders/docx_loader.py
document_loaders/factory.py
document_loaders/json_loader.py
document_loaders/markdown_loader.py
document_loaders/pdf_loader.py
document_loaders/text_loader.py
llm_model/__init__.py
llm_model/base.py
llm_model/chat.py
llm_model/embeddings.py
llm_model/implementations.py
llm_model/llm_manager.py
llm_model/llm_service.py
preprocessor/__init__.py
preprocessor/antlr_parser/__init__.py
preprocessor/antlr_parser/parse_tree.py
preprocessor/antlr_parser/mysql_parser/MySqlLexer.py
preprocessor/antlr_parser/mysql_parser/MySqlParser.py
preprocessor/antlr_parser/mysql_parser/MySqlParserListener.py
preprocessor/antlr_parser/mysql_parser/__init__.py
preprocessor/antlr_parser/oracle_parser/PlSqlLexer.py
preprocessor/antlr_parser/oracle_parser/PlSqlLexerBase.py
preprocessor/antlr_parser/oracle_parser/PlSqlParser.py
preprocessor/antlr_parser/oracle_parser/PlSqlParserBase.py
preprocessor/antlr_parser/oracle_parser/PlSqlParserListener.py
preprocessor/antlr_parser/oracle_parser/__init__.py
preprocessor/antlr_parser/oracle_parser/transformGrammar.py
preprocessor/antlr_parser/pg_parser/LexerDispatchingErrorListener.py
preprocessor/antlr_parser/pg_parser/ParserDispatchingErrorListener.py
preprocessor/antlr_parser/pg_parser/PostgreSQLLexer.py
preprocessor/antlr_parser/pg_parser/PostgreSQLLexerBase.py
preprocessor/antlr_parser/pg_parser/PostgreSQLParser.py
preprocessor/antlr_parser/pg_parser/PostgreSQLParserBase.py
preprocessor/antlr_parser/pg_parser/PostgreSQLParserListener.py
cracksql-0.0.0.dist-info/METADATA
cracksql-0.0.0.dist-info/WHEEL
cracksql-0.0.0.dist-info/top_level.txt
cracksql-0.0.0.dist-info/RECORD
